<Network Fitness="8.43691264702947840703" SpeciesID="-1" UserData="" Distance="1.06556698647236425259" Bodyheight="0.11155188005495113301">
    <Nodes>
        <Node ID="0" Enabled="1" Name="X1" Type="NetworkSensor" DrawingPosition="0.00000000000000000000" TopologyFrozen="0" ActivationFunction="0" />
        <Node ID="1" Enabled="1" Name="Y1" Type="NetworkSensor" DrawingPosition="0.00000000000000000000" TopologyFrozen="0" ActivationFunction="0" />
        <Node ID="2" Enabled="1" Name="Z1" Type="NetworkSensor" DrawingPosition="0.00000000000000000000" TopologyFrozen="0" ActivationFunction="0" />
        <Node ID="3" Enabled="1" Name="X2" Type="NetworkSensor" DrawingPosition="0.00000000000000000000" TopologyFrozen="0" ActivationFunction="0" />
        <Node ID="4" Enabled="1" Name="Y2" Type="NetworkSensor" DrawingPosition="0.00000000000000000000" TopologyFrozen="0" ActivationFunction="0" />
        <Node ID="5" Enabled="1" Name="Z2" Type="NetworkSensor" DrawingPosition="0.00000000000000000000" TopologyFrozen="0" ActivationFunction="0" />
        <Node ID="6" Enabled="1" Name="Bias" Type="NetworkSensor" DrawingPosition="0.00000000000000000000" TopologyFrozen="0" ActivationFunction="0" />
        <Node ID="7" Enabled="1" Name="DeltaX" Type="NetworkSensor" DrawingPosition="0.00000000000000000000" TopologyFrozen="0" ActivationFunction="0" />
        <Node ID="8" Enabled="1" Name="DeltaY" Type="NetworkSensor" DrawingPosition="0.00000000000000000000" TopologyFrozen="0" ActivationFunction="0" />
        <Node ID="9" Enabled="1" Name="DeltaZ" Type="NetworkSensor" DrawingPosition="0.00000000000000000000" TopologyFrozen="0" ActivationFunction="0" />
        <Node ID="10" Enabled="1" Name="T1" Type="NetworkSensor" DrawingPosition="0.00000000000000000000" TopologyFrozen="0" ActivationFunction="0" />
        <Node ID="11" Enabled="1" Name="T2" Type="NetworkSensor" DrawingPosition="0.00000000000000000000" TopologyFrozen="0" ActivationFunction="0" />
        <Node ID="12" Enabled="1" Name="DeltaT" Type="NetworkSensor" DrawingPosition="0.00000000000000000000" TopologyFrozen="0" ActivationFunction="0" />
        <Node ID="13" Enabled="1" Name="Output" Type="NetworkOutputNode" DrawingPosition="1.00000000000000000000" TopologyFrozen="0" ActivationFunction="0" />
        <Node ID="14" Enabled="1" Name="Bias_out" Type="NetworkOutputNode" DrawingPosition="1.00000000000000000000" TopologyFrozen="0" ActivationFunction="0" />
    </Nodes>
    <Links>
        <Link ID="0" Enabled="1" fromNode="0" toNode="13" weight="-2.72115876104887588482" fixed="0" />
        <Link ID="1" Enabled="1" fromNode="0" toNode="14" weight="3.70101415056495586242" fixed="0" />
        <Link ID="2" Enabled="1" fromNode="1" toNode="13" weight="-4.58079545193108828016" fixed="0" />
        <Link ID="3" Enabled="1" fromNode="1" toNode="14" weight="-2.47345178128043485799" fixed="0" />
        <Link ID="4" Enabled="1" fromNode="2" toNode="13" weight="0.72258099473122328060" fixed="0" />
        <Link ID="5" Enabled="1" fromNode="2" toNode="14" weight="-1.79654543460773163943" fixed="0" />
        <Link ID="6" Enabled="1" fromNode="3" toNode="13" weight="0.95903921510238432369" fixed="0" />
        <Link ID="7" Enabled="1" fromNode="3" toNode="14" weight="-3.14525825021088678568" fixed="0" />
        <Link ID="8" Enabled="1" fromNode="4" toNode="13" weight="-1.65534981835742733836" fixed="0" />
        <Link ID="9" Enabled="1" fromNode="4" toNode="14" weight="2.59854640238161405108" fixed="0" />
        <Link ID="10" Enabled="1" fromNode="5" toNode="13" weight="-1.85639762054064427765" fixed="0" />
        <Link ID="11" Enabled="1" fromNode="5" toNode="14" weight="-0.08332081390928569586" fixed="0" />
        <Link ID="12" Enabled="1" fromNode="6" toNode="13" weight="-0.07935631597135972548" fixed="0" />
        <Link ID="13" Enabled="1" fromNode="6" toNode="14" weight="0.49384236256422553435" fixed="0" />
        <Link ID="14" Enabled="1" fromNode="7" toNode="13" weight="-0.46208661830592401287" fixed="0" />
        <Link ID="15" Enabled="1" fromNode="7" toNode="14" weight="-3.07989106900493148089" fixed="0" />
        <Link ID="16" Enabled="1" fromNode="8" toNode="13" weight="0.25822317731286259512" fixed="0" />
        <Link ID="17" Enabled="1" fromNode="8" toNode="14" weight="-0.65108946909599862973" fixed="0" />
        <Link ID="18" Enabled="1" fromNode="9" toNode="13" weight="2.23940681829030463490" fixed="0" />
        <Link ID="19" Enabled="1" fromNode="9" toNode="14" weight="-1.64628721870762539936" fixed="0" />
        <Link ID="20" Enabled="1" fromNode="10" toNode="13" weight="1.40799543680340466523" fixed="0" />
        <Link ID="21" Enabled="1" fromNode="10" toNode="14" weight="1.08049380762689839486" fixed="0" />
        <Link ID="22" Enabled="1" fromNode="11" toNode="13" weight="4.34267295137281195139" fixed="0" />
        <Link ID="23" Enabled="1" fromNode="11" toNode="14" weight="0.41282598586559671183" fixed="0" />
        <Link ID="24" Enabled="1" fromNode="12" toNode="13" weight="-0.92376934036256352911" fixed="0" />
        <Link ID="25" Enabled="1" fromNode="12" toNode="14" weight="5.00000000000000000000" fixed="0" />
    </Links>
    <collisions total="3.00000000000000000000" totaltouchtime="262.00000000000000000000">
        <collision obstacle="OBSTACLE_20" touchtime="94" />
        <collision obstacle="OBSTACLE_5" touchtime="142" />
        <collision obstacle="OBSTACLE_6" touchtime="26" />
    </collisions>
</Network>
